<ui_texture>
     <file_name>ui\ui_inv_character_info</file_name>
     <texture id="ui_inv_character_info_back" x="0" y="0" width="136" height="256"  />
     <texture id="ui_inv_character_info_blood" x="152" y="0" width="12" height="222"  />
     <texture id="ui_inv_character_info_blood_empty" x="165" y="0" width="12" height="222"  />
     <texture id="ui_inv_character_info_endurance" x="178" y="0" width="12" height="222"  />
     <texture id="ui_inv_character_info_endurance_empty" x="191" y="0" width="12" height="222"  />
     <texture id="ui_inv_character_info_radioactivity" x="204" y="0" width="12" height="222"  />
     <texture id="ui_inv_character_info_radioactivity_empty" x="217" y="0" width="12" height="222"  />
     <texture id="ui_inv_character_info_food" x="230" y="0" width="12" height="222"  />
     <texture id="ui_inv_character_info_food_empty" x="243" y="0" width="12" height="222"  />
     <texture id="ui_inv_character_info_water" x="256" y="0" width="12" height="222"  />
     <texture id="ui_inv_character_info_water_empty" x="269" y="0" width="12" height="222"  />
     <texture id="ui_inv_character_info_armor" x="282" y="0" width="12" height="222"  />
     <texture id="ui_inv_character_info_armor_empty" x="295" y="0" width="12" height="222"  />
</ui_texture>
