<ui_texture>
     <file_name>ui\ui_pda_back_big</file_name>
     <texture id="ui_PDA" x="0" y="0" width="910" height="645"  />
     <texture id="ui_PDA_button_close_e" x="0" y="660" width="41" height="21"  />
     <texture id="ui_PDA_button_close_t" x="41" y="660" width="41" height="21"  />
     <texture id="ui_PDA_button_close_h" x="82" y="660" width="41" height="21"  />
     <texture id="ui_PDA_timer_b" x="0" y="715" width="16" height="28"  />
     <texture id="ui_PDA_timer_back" x="16" y="715" width="91" height="28"  />
     <texture id="ui_PDA_timer_e" x="107" y="715" width="17" height="28"  />
     <texture id="ui_PDA_led_yellow" x="126" y="660" width="16" height="9"  />
     <texture id="ui_PDA_led_blue" x="126" y="670" width="16" height="9"  />
     <texture id="ui_PDA_led_red" x="126" y="680" width="16" height="9"  />
     <texture id="ui_PDA_led_green" x="126" y="690" width="16" height="9"  />
     <texture id="ui_PDA_led_orange" x="126" y="700" width="16" height="9"  />
     <texture id="ui_PDA_marker_frame" x="152" y="660" width="312" height="183"  />
     <texture id="ui_PDA_marker_inner_frame" x="474" y="663" width="290" height="82"  />
     <texture id="ui_PDA_marker_btn_left_e" x="474" y="745" width="30" height="80"  />
     <texture id="ui_PDA_marker_btn_right_e" x="504" y="745" width="30" height="80"  />
     <texture id="ui_PDA_marker_btn_left_h" x="534" y="745" width="30" height="80"  />
     <texture id="ui_PDA_marker_btn_right_h" x="564" y="745" width="30" height="80"  />
     <texture id="ui_PDA_marker_btn_left_t" x="594" y="745" width="30" height="80"  />
     <texture id="ui_PDA_marker_btn_right_t" x="624" y="745" width="30" height="80"  />
     <texture id="ui_PDA_marker_btn_left_d" x="654" y="745" width="30" height="80"  />
     <texture id="ui_PDA_marker_btn_right_d" x="684" y="745" width="30" height="80"  />
     <texture id="ui_PDA_button_e" x="774" y="663" width="140" height="32"  />
     <texture id="ui_PDA_button_h" x="774" y="695" width="140" height="32"  />
     <texture id="ui_PDA_button_t" x="774" y="727" width="140" height="32"  />
     <texture id="ui_PDA_button_d" x="774" y="759" width="140" height="32"  />
     <texture id="ui_pda_marker_field_b" x="474" y="825" width="10" height="27"  />
     <texture id="ui_pda_marker_field_back" x="484" y="825" width="10" height="27"  />
     <texture id="ui_pda_marker_field_e" x="754" y="825" width="10" height="27"  />
     <texture id="ui_pda_btn_quests_e" x="152" y="860" width="40" height="20"  />
     <texture id="ui_pda_btn_quests_h" x="152" y="880" width="40" height="20"  />
     <texture id="ui_pda_btn_quests_t" x="152" y="900" width="40" height="20"  />
     <texture id="ui_pda_btn_quests_d" x="152" y="920" width="40" height="20"  />
     <texture id="ui_pda_btn_map_e" x="192" y="860" width="40" height="20"  />
     <texture id="ui_pda_btn_map_h" x="192" y="880" width="40" height="20"  />
     <texture id="ui_pda_btn_map_t" x="192" y="900" width="40" height="20"  />
     <texture id="ui_pda_btn_map_d" x="192" y="920" width="40" height="20"  />
     <texture id="ui_pda_btn_diary_e" x="232" y="860" width="40" height="20"  />
     <texture id="ui_pda_btn_diary_h" x="232" y="880" width="40" height="20"  />
     <texture id="ui_pda_btn_diary_t" x="232" y="900" width="40" height="20"  />
     <texture id="ui_pda_btn_diary_d" x="232" y="920" width="40" height="20"  />
     <texture id="ui_pda_btn_contacts_e" x="272" y="860" width="40" height="20"  />
     <texture id="ui_pda_btn_contacts_h" x="272" y="880" width="40" height="20"  />
     <texture id="ui_pda_btn_contacts_t" x="272" y="900" width="40" height="20"  />
     <texture id="ui_pda_btn_contacts_d" x="272" y="920" width="40" height="20"  />
     <texture id="ui_pda_btn_ranking_e" x="312" y="860" width="40" height="20"  />
     <texture id="ui_pda_btn_ranking_h" x="312" y="880" width="40" height="20"  />
     <texture id="ui_pda_btn_ranking_t" x="312" y="900" width="40" height="20"  />
     <texture id="ui_pda_btn_ranking_d" x="312" y="920" width="40" height="20"  />
     <texture id="ui_pda_btn_statistics_e" x="352" y="860" width="40" height="20"  />
     <texture id="ui_pda_btn_statistics_h" x="352" y="880" width="40" height="20"  />
     <texture id="ui_pda_btn_statistics_t" x="352" y="900" width="40" height="20"  />
     <texture id="ui_pda_btn_statistics_d" x="352" y="920" width="40" height="20"  />
     <texture id="ui_pda_btn_encyclopedia_e" x="392" y="860" width="40" height="20"  />
     <texture id="ui_pda_btn_encyclopedia_h" x="392" y="880" width="40" height="20"  />
     <texture id="ui_pda_btn_encyclopedia_t" x="392" y="900" width="40" height="20"  />
     <texture id="ui_pda_btn_encyclopedia_d" x="392" y="920" width="40" height="20"  />
     <texture id="ui_pda_btn_base_skills_e" x="432" y="860" width="40" height="20"  />
     <texture id="ui_pda_btn_base_skills_h" x="432" y="880" width="40" height="20"  />
     <texture id="ui_pda_btn_base_skills_t" x="432" y="900" width="40" height="20"  />
     <texture id="ui_pda_btn_base_skills_d" x="432" y="920" width="40" height="20"  />
     <texture id="ui_pda_btn_base_downloads_e" x="472" y="860" width="40" height="20"  />
     <texture id="ui_pda_btn_base_downloads_h" x="472" y="880" width="40" height="20"  />
     <texture id="ui_pda_btn_base_downloads_t" x="472" y="900" width="40" height="20"  />
     <texture id="ui_pda_btn_base_downloads_d" x="472" y="920" width="40" height="20"  />
     <texture id="ui_pda_btn_base_tetris_e" x="512" y="860" width="40" height="20"  />
     <texture id="ui_pda_btn_base_tetris_h" x="512" y="880" width="40" height="20"  />
     <texture id="ui_pda_btn_base_tetris_t" x="512" y="900" width="40" height="20"  />
     <texture id="ui_pda_btn_base_tetris_d" x="512" y="920" width="40" height="20"  />
     <texture id="ui_pda_btn_base_mplayer_e" x="552" y="860" width="40" height="20"  />
     <texture id="ui_pda_btn_base_mplayer_h" x="552" y="880" width="40" height="20"  />
     <texture id="ui_pda_btn_base_mplayer_t" x="552" y="900" width="40" height="20"  />
     <texture id="ui_pda_btn_base_mplayer_d" x="552" y="920" width="40" height="20"  />
</ui_texture>
