<?xml version="1.0" encoding="windows-1251" ?>
<game_dialogs>
	<dialog id="crow_hunter_mg">
        <phrase_list>
			<phrase id="0">
				<next>100</next>
			</phrase>
			<phrase id="100">
				<next>200</next>
				<next>23</next>
			</phrase>
			<phrase id="200">
				<precondition>crow_hunter.is_ready</precondition>
				<text>st_cr_0000</text>
				<next>1</next>
				<next>2</next>
			</phrase>
			<phrase id="1">
				<text>st_cr_0001</text>
				<action>crow_hunter.init_if_needed</action>
				<next>3</next>
			</phrase>
			<phrase id="2">
				<text>st_cr_0002</text>
				<action>dialogs.break_dialog</action>
			</phrase>
			<phrase id="3">
				<text>st_cr_0003</text>
				<next>4</next>
				<!-- <next>5</next> -->
				<next>6</next>
			</phrase>
			<phrase id="4">
				<text>st_cr_0004</text>
				<action>crow_hunter.select_mode_one</action>
				<next>7</next>
			</phrase>
			<phrase id="5">
				<text>st_cr_0005</text>
				<action>crow_hunter.select_mode_two</action>
				<next>21</next>
			</phrase>
			<phrase id="6">
				<text>st_cr_0006</text>
				<action>dialogs.break_dialog</action>
			</phrase>
			<phrase id="7">
				<text>st_cr_0007</text>
				<next>8</next>
				<next>9</next>
				<next>10</next>
				<next>6</next>
			</phrase>
			<phrase id="8">
				<text>st_cr_0008</text>
				<action>crow_hunter.select_easy</action>
				<next>11</next>
			</phrase>
			<phrase id="9">
				<text>st_cr_0009</text>
				<action>crow_hunter.select_normal</action>
				<next>11</next>
			</phrase>
			<phrase id="10">
				<text>st_cr_0010</text>
				<action>crow_hunter.select_hard</action>
				<next>11</next>
			</phrase>
			<phrase id="11">
				<text>st_cr_0011</text>
				<next>12</next>
				<next>13</next>
				<next>14</next>
				<next>15</next>
				<next>16</next>
				<next>17</next>
				<next>18</next>
				<next>19</next>
				<next>6</next>
			</phrase>
			<phrase id="12">
				<text>st_cr_0012</text>
				<precondition>crow_hunter.check_l1</precondition>
				<action>crow_hunter.select_l1</action>
				<next>20</next>
			</phrase>
			<phrase id="13">
				<text>st_cr_0013</text>
				<precondition>crow_hunter.check_l2</precondition>
				<action>crow_hunter.select_l2</action>
				<next>20</next>
			</phrase>
			<phrase id="14">
				<text>st_cr_0014</text>
				<precondition>crow_hunter.check_l3</precondition>
				<action>crow_hunter.select_l3</action>
				<next>20</next>
			</phrase>
			<phrase id="15">
				<text>st_cr_0015</text>
				<precondition>crow_hunter.check_l4</precondition>
				<action>crow_hunter.select_l4</action>
				<next>20</next>
			</phrase>
			<phrase id="16">
				<text>st_cr_0016</text>
				<precondition>crow_hunter.check_l5</precondition>
				<action>crow_hunter.select_l5</action>
				<next>20</next>
			</phrase>
			<phrase id="17">
				<text>st_cr_0017</text>
				<precondition>crow_hunter.check_l6</precondition>
				<action>crow_hunter.select_l6</action>
				<next>20</next>
			</phrase>
			<phrase id="18">
				<text>st_cr_0018</text>
				<precondition>crow_hunter.check_l7</precondition>
				<action>crow_hunter.select_l7</action>
				<next>20</next>
			</phrase>
			<phrase id="19">
				<text>st_cr_0019</text>
				<precondition>crow_hunter.check_l8</precondition>
				<action>crow_hunter.select_l8</action>
				<next>20</next>
			</phrase>
			<phrase id="20">
				<text>st_cr_0020</text>
				<!-- <action>crow_hunter.start_mgame</action>
				<action>dialogs.break_dialog</action> -->
				<next>21</next>
			</phrase>
			<phrase id="21">
				<text>st_cr_0021</text>
				<next>22</next>
			</phrase>
			<phrase id="22">
				<text>st_cr_0022</text>
				<action>crow_hunter.start_mgame</action>
				<action>dialogs.break_dialog</action>
			</phrase>
			<phrase id="23">
				<precondition>crow_hunter.is_stopped</precondition>
				<text>st_cr1_0000</text>
				<action>crow_hunter.show_result</action>
				<next>24</next>
			</phrase>
			<phrase id="24">
				<text>st_cr1_0001</text>
				<next>25</next>
			</phrase>
			<phrase id="25">
				<text>st_cr1_0002</text>
				<next>26</next>
				<next>27</next>
			</phrase>
			<phrase id="26">
				<text>st_cr1_0002</text>
				<action>crow_hunter.resume</action>
			</phrase>
			<phrase id="27">
				<text>st_cr_0002</text>
				<action>crow_hunter.resume</action>
			</phrase>
		</phrase_list>
	</dialog>
</game_dialogs>
			
			
			
			
			
			
			