<?xml version='1.0' encoding="windows-1251"?>

<xml>
	<!-- MILITARY CHARACTER PROFILES -->
	
	<!-- ************************** novice ************************** -->


<!-- lox start -->

	<specific_character id="mil_crazy_stalker" team_default = "1">
		<name>mil_crazy_stalker_name</name>
		<icon>ui_npc_u_stalker_bandit_coat_mask_02</icon>
		<map_icon x="3" y="2"></map_icon>
		<bio>mil_crazy_stalker_bio</bio>
		<class>mil_crazy_stalker</class>
		<community>stranger</community>
		
		<rank>889</rank>
		<reputation>-156</reputation>

		<visual>actors\bandit\stalker_bandit_coat_mask_02</visual>
		<snd_config>characters_voice\human_02\bandit\</snd_config>
		<supplies>
			<include id="bandit_t1_veteran"/>
			<include id="stalker_general_common"/>
		</supplies>
		<start_dialog>mil_crazy_stalker_job</start_dialog>
		<actor_dialog>mil_crazy_stalker_job_done</actor_dialog>
		<actor_dialog>mil_crazy_stalker_info</actor_dialog>
	</specific_character>		
		
	<specific_character id="military_supplier" no_random = "1">
		<name>mil_ugrymiy_name</name>
		<icon>ui_npc_u_stalker_neutral_uniq_face_01</icon>
		<map_icon x="1" y="4"></map_icon>
		<bio>sim_stalker_veteran_bio</bio>

		<class>military_supplier</class>
		<community>trader</community>
		<money min="1000000" max="1000000" infinitive="1"></money>
		
		<map_spot_pointer>trader_map_spot</map_spot_pointer>
		
		<rank>1700</rank>
		<reputation>500</reputation>
		<visual>actors\neutral\stalker_neutral_uniq_face_01</visual>
		<snd_config>characters_voice\human_01\stalker\</snd_config>
		<crouch_type>-1</crouch_type>
		
		<supplies>
		</supplies>

		<start_dialog>mil_basement_trader_info</start_dialog>
		<actor_dialog>tm_mil_supplier_dialog</actor_dialog>
		<actor_dialog>tm_mil_supplier_reward</actor_dialog>

		<invulnerable>true</invulnerable>

	</specific_character>

	<specific_character id="mil_camper_base1" team_default = "1">
		<name>GENERATE_NAME_stalker</name>
		<icon>ui_npc_u_stalker_killer_medium_mask_01</icon>
		<map_icon x="2" y="0"></map_icon>
		<bio>cit_killer_general_bio</bio>

		<class>mil_camper_base1</class>
		<community>killer</community> <terrain_sect>stalker_killer_terrain</terrain_sect>

		<rank>844</rank>
		<reputation>-137</reputation>
		
		<snd_config>characters_voice\human_02\killer\</snd_config>
		
		<visual>actors\killer\stalker_killer_medium_mask_01</visual>
		<supplies>
			<include id="killer_t2_sniper"/>
		</supplies>
					
	</specific_character>
	<specific_character id="mil_camper_base2" team_default = "1">
		<name>GENERATE_NAME_stalker</name>
		<icon>ui_npc_u_stalker_killer_medium_mask_02</icon>
		<map_icon x="2" y="0"></map_icon>
		<bio>cit_killer_general_bio</bio>

		<class>mil_camper_base2</class>
		<community>killer</community> <terrain_sect>stalker_killer_terrain</terrain_sect>

		<rank>765</rank>
		<reputation>-129</reputation>
		
		<snd_config>characters_voice\human_02\killer\</snd_config>
		
		<visual>actors\killer\stalker_killer_medium_mask_04</visual>
		<supplies>
			<include id="killer_t2_sniper"/>
		</supplies>
					
	</specific_character>
	<specific_character id="cit_killer_leader_god" team_default = "1">
		<name>mil_mad_dog_name</name>
		<icon>ui_npc_u_stalker_killer_uniq_face_01</icon>
		<map_icon x="2" y="0"></map_icon>
		<bio>mil_mad_dog_bio</bio>

		<class>cit_killer_leader_god</class>
		<community>killer</community> <terrain_sect>stalker_killer_terrain</terrain_sect>
		
		<rank>999</rank>
		<reputation>-150</reputation>
	
		<snd_config>characters_voice\human_02\killer\</snd_config>
		
		<visual>actors\killer\stalker_killer_uniq_face_01</visual>
		<supplies>
			<include id="killer_t2_sniper"/>
			<item s="cit_leader_killer_pda"/>
			<include id="killer_master_common"/>
		</supplies>
					
	</specific_character>

	<specific_character id="mil_ghost" team_default = "1">
		<name>mil_ghost_name</name>
		<icon>ui_npc_u_stalker_neutral_uniq_ghost</icon>
		<map_icon x="0" y="6"></map_icon>
		<bio>mil_ghost_bio</bio>

		<class>yan_ghost</class>
		<community>stalker</community> <terrain_sect>stalker_terrain</terrain_sect>
		<money min="2000" max="4000" infinitive="0"></money>

		
		<rank>721</rank>
		<reputation>150</reputation>

		<visual>actors\neutral\stalker_neutral_uniq_ghost</visual>
		<snd_config>characters_voice\human_01\stalker\</snd_config>
		<crouch_type>1</crouch_type>
		<supplies>
			<include id="item_binoc"/>
			<include id="dolg_t3_master_machinegun"/>
			<include id="dolg_t3_master_sidearm"/>
			<include id="dolg_master_common"/>
		</supplies>
	<!--	<start_dialog>mil_ghost_dialog_cristal</start_dialog> -->
		<actor_dialog>gen_ghost_plan</actor_dialog>
		<actor_dialog>gen_ghost_final_dialog</actor_dialog>
		<actor_dialog>gen_ghost_postfinal</actor_dialog>
		<actor_dialog>dm_help_wounded_medkit_dialog</actor_dialog>	
   <!-- <actor_dialog>mil_ghost_dialog_cristal_end</actor_dialog> -->

</specific_character>
<specific_character id="mil_contact" team_default = "1">
		<name>mil_contact_name</name>
		<icon>ui_npc_u_stalker_svoboda_uniq_face_02</icon>
		<map_icon x="0" y="6"></map_icon>
		<bio>sim_stalker_veteran_bio</bio>

		<class>mil_contact</class>
		<community>stalker</community> <terrain_sect>stalker_terrain</terrain_sect>

		<panic_threshold>0</panic_threshold>
		<rank>778</rank>
		<reputation>70</reputation>

		<visual>actors\svoboda\stalker_svoboda_uniq_face_02</visual>
		<snd_config>characters_voice\human_01\stalker\</snd_config>
		<crouch_type>1</crouch_type>
		<supplies>
			<include id="stalker_t2_veteran_auto"/>
		</supplies>
		<invulnerable>true</invulnerable>
		<start_dialog>mil_contact_cristall</start_dialog>
</specific_character>

	<specific_character id="actor_exebition" >
		<name>GENERATE_NAME_stalker</name>
		<icon>ui_npc_u_actor</icon>
		<map_icon x="2" y="5"></map_icon>

		<community>stranger</community> 
		<class>actor_exebition</class>
		<snd_config>characters_voice\human_02\killer\</snd_config>
		<crouch_type>-1</crouch_type>
	
		<rank>00</rank>
		<reputation>0</reputation>
		<visual>actors\hero\hero_stalker_medium</visual>
		
		<supplies>
			<item s="hand_radio"/>
			<item s="sar_brick"/>
		</supplies>
		
	</specific_character>

	<specific_character id="actor_exebition2" >
		<name>GENERATE_NAME_stalker</name>
		<icon>ui_npc_u_actor</icon>
		<map_icon x="2" y="5"></map_icon>

		<community>stalker</community> 
		<supplies>
			<item s="hand_radio"/>
			<item s="sar_brick"/>
		</supplies>
		
                <team>stalker</team>
		<class>actor_exebition2</class>
		<community>actor</community>
		<snd_config>characters_voice\human_02\killer\</snd_config>
		<crouch_type>-1</crouch_type>
	
		<rank>00</rank>
		<reputation>0</reputation>
		<visual>actors\hero\hero_stalker_medium</visual>
	</specific_character>
	<specific_character id="mil_killer_exebition_1" team_default="1">
		<name>GENERATE_NAME_stalker</name>
		<icon>ui_npc_u_stalker_killer_medium_mask_01</icon>
		<map_icon x="2" y="0"></map_icon>
		<bio>sim_killer_general_bio</bio>

		<team>Killer_regular</team>

		<class>mil_killer_exebition_1</class>
		<community>killer</community> <terrain_sect>stalker_killer_terrain</terrain_sect>

		<rank>321</rank>
		<reputation>-63</reputation>
		
		<snd_config>characters_voice\human_02\killer\</snd_config>
		<crouch_type>-1</crouch_type>
		<visual>actors\killer\stalker_killer_medium_mask_01</visual>
		<supplies>
			<include id="killer_t2_regular"/>
		</supplies>
	</specific_character>
	<specific_character id="mil_killer_exebition_2" team_default="1">
		<name>GENERATE_NAME_stalker</name>
		<icon>ui_npc_u_stalker_killer_medium_mask_01</icon>
		<map_icon x="2" y="0"></map_icon>
		<bio>sim_killer_general_bio</bio>

		<team>Killer_regular</team>

		<class>mil_killer_exebition_2</class>
		<community>killer</community> <terrain_sect>stalker_killer_terrain</terrain_sect>

		<rank>321</rank>
		<reputation>-61</reputation>
		
		<snd_config>characters_voice\human_02\killer\</snd_config>
		<crouch_type>-1</crouch_type>
		<visual>actors\killer\stalker_killer_uniq_face_03</visual>
		<supplies>
			<include id="killer_t2_regular"/>
		</supplies>
	</specific_character>
<!-- lox end -->
	
	<!-- FANG -->
	<specific_character id="mil_fang" team_default = "1">
		<name>mil_fang_name</name>
		<icon>ui_npc_u_stalker_neutral_uniq_fang</icon>
		<map_icon x="0" y="6"></map_icon>
		<bio>mil_fang_bio</bio>

		<class>mil_fang</class>
		<community>stalker</community> <terrain_sect>stalker_terrain</terrain_sect>

		
		<rank>750</rank>
		<reputation>150</reputation>

		<visual>actors\neutral\stalker_neutral_uniq_fang</visual>
		<snd_config>characters_voice\human_01\stalker\</snd_config>
		<crouch_type>1</crouch_type>
		<supplies>
			<include id="stalker_t2_veteran_auto"/>
		</supplies>
		<start_dialog>mil_fang_dialog</start_dialog>
		<actor_dialog>dm_hello_dialog</actor_dialog>
</specific_character>
	
	
	<specific_character id="prof_soldier_novice_default1" team_default="1">
		<name>GENERATE_NAME_private</name>
		<icon>ui_npc_u_stalker_military_light_bandana_03</icon> <!--<icon>npc_icon_soldier_private</icon>-->
		<bio>prof_soldier_novice_bio</bio>
		
		<class>prof_soldier_novice</class>
		<community>military</community>
		
		<terrain_sect>stalker_military_terrain</terrain_sect>
		<critical_wound_weights>55,30,15</critical_wound_weights>
		
		<crouch_type>-1</crouch_type>
		<panic_threshold>0</panic_threshold>
		<money min="100" max="500" infinitive="0"/>
		
		<rank>100</rank>
		<reputation>5</reputation>
		
		<snd_config>characters_voice\human_01\military\</snd_config>
		<visual>actors\military\stalker_military_light_bandana_03</visual>
		
		<supplies>
			<include id="soldier_t1_regular"/>
		</supplies>
		
	</specific_character>
	<specific_character id="prof_soldier_novice_default2" team_default="1">
		<name>GENERATE_NAME_private</name>
		<icon>ui_npc_u_stalker_military_light_bandana_01</icon> <!--<icon>npc_icon_soldier_private</icon>-->
		<bio>prof_soldier_novice_bio</bio>
		
		<class>prof_soldier_novice</class>
		<community>military</community>
		
		<terrain_sect>stalker_military_terrain</terrain_sect>
		<critical_wound_weights>55,30,15</critical_wound_weights>
		
		<crouch_type>-1</crouch_type>
		<panic_threshold>0</panic_threshold>
		<money min="200" max="600" infinitive="0"/>
		
		<rank>150</rank>
		<reputation>10</reputation>
		
		<snd_config>characters_voice\human_01\military\</snd_config>
		<visual>actors\military\stalker_military_light_bandana_01</visual>
		
		<supplies>
			<include id="soldier_t1_regular"/>
		</supplies>
		
	</specific_character>
	<specific_character id="prof_soldier_novice_default3" team_default="1">
		<name>GENERATE_NAME_private</name>
		<icon>ui_npc_u_stalker_military_light_bandana_05</icon> <!--<icon>npc_icon_soldier_private</icon>-->
		<bio>prof_soldier_novice_bio</bio>
		
		<class>prof_soldier_novice</class>
		<community>military</community>
		
		<terrain_sect>stalker_military_terrain</terrain_sect>
		<critical_wound_weights>55,30,15</critical_wound_weights>
		
		<crouch_type>-1</crouch_type>
		<panic_threshold>0</panic_threshold>
		<money min="200" max="700" infinitive="0"/>
		
		<rank>215</rank>
		<reputation>4</reputation>
		
		<snd_config>characters_voice\human_01\military\</snd_config>
		<visual>actors\military\stalker_military_light_bandana_05</visual>
		
		<supplies>
			<include id="soldier_t2_regular"/>
		</supplies>
		
	</specific_character>
	<specific_character id="mil_killer_sergey" team_default="1">
		<name>mil_killer_sergey_name</name>
		<icon>ui_npc_u_stalker_killer_uniq_agent</icon>
		<map_icon x="2" y="0"></map_icon>
		<bio>sim_killer_general_bio</bio>

		<class>mil_killer_sergey</class>
		<community>killer</community> <terrain_sect>stalker_killer_terrain</terrain_sect>

		<rank>321</rank>
		<reputation>-63</reputation>
		
		<snd_config>characters_voice\human_02\killer\</snd_config>
		<crouch_type>-1</crouch_type>
		<visual>actors\killer\stalker_killer_uniq_agent</visual>
		<supplies>
			<include id="weapon_ak74"/>
			<include id="weapon_walther"/>
			<include id="killer_veteran_common"/>
		</supplies>
		
#include "gameplay\character_criticals_4.xml"
	</specific_character>
	<specific_character id="prof_soldier_novice_default4" team_default="1">
		<name>GENERATE_NAME_private</name>
		<icon>ui_npc_u_soldier_bandana_2</icon> <!--<icon>npc_icon_soldier_private</icon>-->
		<bio>prof_soldier_novice_bio</bio>
		
		<class>prof_soldier_novice</class>
		<community>military</community>
		
		<terrain_sect>stalker_military_terrain</terrain_sect>
		<critical_wound_weights>55,30,15</critical_wound_weights>
		
		<crouch_type>-1</crouch_type>
		<panic_threshold>0</panic_threshold>
		<money min="200" max="800" infinitive="0"/>
		
		<rank>130</rank>
		<reputation>15</reputation>
		
		<snd_config>characters_voice\human_01\military\</snd_config>
		<visual>actors\military\stalker_military_light_bandana_02</visual>
		
		<supplies>
			<include id="soldier_t1_regular"/>
		</supplies>
		
	</specific_character>
	<specific_character id="prof_soldier_novice_default5" team_default="1">
		<name>GENERATE_NAME_private</name>
		<icon>ui_npc_u_stalker_military_light_bandana_02</icon> <!--<icon>npc_icon_soldier_private</icon>-->
		<bio>prof_soldier_novice_bio</bio>
		
		<class>prof_soldier_novice</class>
		<community>military</community>
		
		<terrain_sect>stalker_military_terrain</terrain_sect>
		<critical_wound_weights>55,30,15</critical_wound_weights>
		
		<crouch_type>-1</crouch_type>
		<panic_threshold>0</panic_threshold>
		<money min="200" max="900" infinitive="0"/>
		
		<rank>223</rank>
		<reputation>6</reputation>
		
		<snd_config>characters_voice\human_01\military\</snd_config>
		<visual>actors\military\stalker_military_light_bandana_02</visual>
		
		<supplies>
			<include id="soldier_t1_regular"/>
		</supplies>
		
	</specific_character>
	<specific_character id="prof_soldier_novice_default6" team_default="1">
		<name>GENERATE_NAME_private</name>
		<icon>ui_npc_u_soldier_bandana_4</icon> <!--<icon>npc_icon_soldier_private</icon>-->
		<bio>prof_soldier_novice_bio</bio>
		
		<class>prof_soldier_novice</class>
		<community>military</community>
		
		<terrain_sect>stalker_military_terrain</terrain_sect>
		<critical_wound_weights>55,30,15</critical_wound_weights>
		
		<crouch_type>-1</crouch_type>
		<panic_threshold>0</panic_threshold>
		<money min="300" max="1000" infinitive="0"/>
		
		<rank>245</rank>
		<reputation>9</reputation>
		
		<snd_config>characters_voice\human_01\military\</snd_config>
		<visual>actors\military\stalker_military_light_bandana_06</visual>
		
		<supplies>
			<include id="soldier_t1_regular"/>
		</supplies>
		
	</specific_character>
	<specific_character id="prof_soldier_novice_default7" team_default="1">
		<name>GENERATE_NAME_private</name>
		<icon>ui_npc_u_stalker_military_light_bandana_05</icon> <!--<icon>npc_icon_soldier_private</icon>-->
		<bio>prof_soldier_novice_bio</bio>
		
		<class>prof_soldier_novice</class>
		<community>military</community>
		
		<terrain_sect>stalker_military_terrain</terrain_sect>
		<critical_wound_weights>55,30,15</critical_wound_weights>
		
		<crouch_type>-1</crouch_type>
		<panic_threshold>0</panic_threshold>
		<money min="200" max="800" infinitive="0"/>
		
		<rank>260</rank>
		<reputation>11</reputation>
		
		<snd_config>characters_voice\human_01\military\</snd_config>
		<visual>actors\military\stalker_military_light_bandana_05</visual>
		
		<supplies>
			<include id="soldier_t1_regular"/>
		</supplies>
		
	</specific_character>
	<specific_character id="prof_soldier_novice_default8" team_default="1">
		<name>GENERATE_NAME_private</name>
		<icon>ui_npc_u_stalker_military_light_bandana_01</icon> <!--<icon>npc_icon_soldier_private</icon>-->
		<bio>prof_soldier_novice_bio</bio>
		
		<class>prof_soldier_novice</class>
		<community>military</community>
		
		<terrain_sect>stalker_military_terrain</terrain_sect>
		<critical_wound_weights>55,30,15</critical_wound_weights>
		
		<crouch_type>-1</crouch_type>
		<panic_threshold>0</panic_threshold>
		<money min="200" max="600" infinitive="0"/>
		
		<rank>278</rank>
		<reputation>-10</reputation>
		
		<snd_config>characters_voice\human_01\military\</snd_config>
		<visual>actors\military\stalker_military_light_bandana_01</visual>
		
		<supplies>
			<include id="soldier_t1_regular"/>
		</supplies>
		
	</specific_character>
	

	
	<!-- ************************** experienced ************************** -->
	
	<specific_character id="prof_soldier_experienced_default1" team_default="1">
		<name>GENERATE_NAME_sergeant</name>
		<icon>ui_npc_u_stalker_military_medium_helmet_01</icon> <!--<icon>ui_npc_u_stalker_military_medium_helmet_01</icon>-->
		<bio>prof_soldier_experienced_bio</bio>
		
		<class>prof_soldier_experienced</class>
		<community>military</community>
		
		<terrain_sect>stalker_military_terrain</terrain_sect>
		<critical_wound_weights>55,30,15</critical_wound_weights>
		<hit_probability_factor>1</hit_probability_factor>
		
		<rank>330</rank>
		<reputation>-20</reputation>
		
		<crouch_type>-1</crouch_type>
		<panic_threshold>0</panic_threshold>
		<money min="1000" max="2000" infinitive="0"/>
		
		<snd_config>characters_voice\human_03\military\</snd_config>
		<visual>actors\military\stalker_military_medium_helmet_01</visual>
		
		<supplies>
			<include id="soldier_t2_regular"/>
		</supplies>
		
	</specific_character>
	<specific_character id="prof_soldier_experienced_default2" team_default="1">
		<name>GENERATE_NAME_lieutenant</name>
		<icon>ui_npc_u_stalker_military_medium_helmet_01</icon> <!--<icon>ui_npc_u_stalker_military_medium_helmet_01</icon>-->
		<bio>prof_soldier_experienced_bio</bio>
		
		<class>prof_soldier_experienced</class>
		<community>military</community>
		
		<terrain_sect>stalker_military_terrain</terrain_sect>
		<critical_wound_weights>55,30,15</critical_wound_weights>
		<hit_probability_factor>1</hit_probability_factor>
		
		<rank>350</rank>
		<reputation>-10</reputation>
		
		<crouch_type>-1</crouch_type>
		<panic_threshold>0</panic_threshold>
		<money min="1000" max="2000" infinitive="0"/>
		
		<snd_config>characters_voice\human_03\military\</snd_config>
		<visual>actors\military\stalker_military_medium_helmet_01</visual>
		
		<supplies>
			<include id="soldier_t2_regular"/>
		</supplies>
		
	</specific_character>
	<specific_character id="prof_soldier_experienced_default3" team_default="1">
		<name>GENERATE_NAME_sergeant</name>
		<icon>ui_npc_u_stalker_military_medium_helmet_01</icon> <!--<icon>ui_npc_u_stalker_military_medium_helmet_01</icon>-->
		<bio>prof_soldier_experienced_bio</bio>
		
		<class>prof_soldier_experienced</class>
		<community>military</community>
		
		<terrain_sect>stalker_military_terrain</terrain_sect>
		<critical_wound_weights>55,30,15</critical_wound_weights>
		<hit_probability_factor>1</hit_probability_factor>
		
		<rank>400</rank>
		<reputation>-5</reputation>
		
		<crouch_type>-1</crouch_type>
		<panic_threshold>0</panic_threshold>
		<money min="1000" max="2000" infinitive="0"/>
		
		<snd_config>characters_voice\human_03\military\</snd_config>
		<visual>actors\military\stalker_military_medium_helmet_01</visual>
		
		<supplies>
			<include id="soldier_t2_regular"/>
		</supplies>
		
	</specific_character>
	<specific_character id="prof_soldier_experienced_default4" team_default="1">
		<name>GENERATE_NAME_lieutenant</name>
		<icon>ui_npc_u_stalker_military_medium_helmet_01</icon> <!--<icon>ui_npc_u_stalker_military_medium_helmet_01</icon>-->
		<bio>prof_soldier_experienced_bio</bio>
		
		<class>prof_soldier_experienced</class>
		<community>military</community>
		
		<terrain_sect>stalker_military_terrain</terrain_sect>
		<critical_wound_weights>55,30,15</critical_wound_weights>
		<hit_probability_factor>1</hit_probability_factor>
		
		<rank>450</rank>
		<reputation>10</reputation>
		
		<crouch_type>-1</crouch_type>
		<panic_threshold>0</panic_threshold>
		<money min="1000" max="2000" infinitive="0"/>
		
		<snd_config>characters_voice\human_03\military\</snd_config>
		<visual>actors\military\stalker_military_medium_helmet_01</visual>
		
		<supplies>
			<include id="soldier_t2_regular"/>
		</supplies>
		
	</specific_character>
	<specific_character id="prof_soldier_experienced_default5" team_default="1">
		<name>GENERATE_NAME_sergeant</name>
		<icon>ui_npc_u_stalker_military_medium_helmet_01</icon> <!--<icon>ui_npc_u_stalker_military_medium_helmet_01</icon>-->
		<bio>prof_soldier_experienced_bio</bio>
		
		<class>prof_soldier_experienced</class>
		<community>military</community>
		
		<terrain_sect>stalker_military_terrain</terrain_sect>
		<critical_wound_weights>55,30,15</critical_wound_weights>
		<hit_probability_factor>1</hit_probability_factor>
		
		<rank>490</rank>
		<reputation>-15</reputation>
		
		<crouch_type>-1</crouch_type>
		<panic_threshold>0</panic_threshold>
		<money min="1000" max="2000" infinitive="0"/>
		
		<snd_config>characters_voice\human_03\military\</snd_config>
		<visual>actors\military\stalker_military_medium_helmet_01</visual>
		
		<supplies>
			<include id="soldier_t2_regular"/>
		</supplies>
		
	</specific_character>
	<specific_character id="prof_soldier_experienced_default6" team_default="1">
		<name>GENERATE_NAME_lieutenant</name>
		<icon>ui_npc_u_stalker_military_medium_helmet_01</icon> <!--<icon>ui_npc_u_stalker_military_medium_helmet_01</icon>-->
		<bio>prof_soldier_experienced_bio</bio>
		
		<class>prof_soldier_experienced</class>
		<community>military</community>
		
		<terrain_sect>stalker_military_terrain</terrain_sect>
		<critical_wound_weights>55,30,15</critical_wound_weights>
		<hit_probability_factor>1</hit_probability_factor>
		
		<rank>500</rank>
		<reputation>-15</reputation>
		
		<crouch_type>-1</crouch_type>
		<panic_threshold>0</panic_threshold>
		<money min="1000" max="2000" infinitive="0"/>
		
		<snd_config>characters_voice\human_03\military\</snd_config>
		<visual>actors\military\stalker_military_medium_helmet_01</visual>
		
		<supplies>
			<include id="soldier_t2_regular"/>
		</supplies>
		
	</specific_character>
	<specific_character id="prof_soldier_experienced_default7" team_default="1">
		<name>GENERATE_NAME_sergeant</name>
		<icon>ui_npc_u_stalker_military_medium_helmet_01</icon> <!--<icon>ui_npc_u_stalker_military_medium_helmet_01</icon>-->
		<bio>prof_soldier_experienced_bio</bio>
		
		<class>prof_soldier_experienced</class>
		<community>military</community>
		
		<terrain_sect>stalker_military_terrain</terrain_sect>
		<critical_wound_weights>55,30,15</critical_wound_weights>
		<hit_probability_factor>1</hit_probability_factor>
		
		<rank>530</rank>
		<reputation>-15</reputation>
		
		<crouch_type>-1</crouch_type>
		<panic_threshold>0</panic_threshold>
		<money min="1000" max="2000" infinitive="0"/>
		
		<snd_config>characters_voice\human_03\military\</snd_config>
		<visual>actors\military\stalker_military_medium_helmet_01</visual>
		
		<supplies>
			<include id="soldier_t2_regular"/>
		</supplies>
		
	</specific_character>
	<specific_character id="prof_soldier_experienced_default8" team_default="1">
		<name>GENERATE_NAME_sergeant</name>
		<icon>ui_npc_u_stalker_military_medium_helmet_01</icon> <!--<icon>ui_npc_u_stalker_military_medium_helmet_01</icon>-->
		<bio>prof_soldier_experienced_bio</bio>
		
		<class>prof_soldier_experienced</class>
		<community>military</community>
		
		<terrain_sect>stalker_military_terrain</terrain_sect>
		<critical_wound_weights>55,30,15</critical_wound_weights>
		<hit_probability_factor>1</hit_probability_factor>
		
		<rank>560</rank>
		<reputation>-20</reputation>
		
		<crouch_type>-1</crouch_type>
		<panic_threshold>0</panic_threshold>
		<money min="1000" max="2000" infinitive="0"/>
		
		<snd_config>characters_voice\human_03\military\</snd_config>
		<visual>actors\military\stalker_military_medium_helmet_01</visual>
		
		<supplies>
			<include id="soldier_t2_regular"/>
		</supplies>
		
	</specific_character>
	
	<!-- ************************** veteran ************************** -->
	
	<specific_character id="prof_soldier_veteran_default1" team_default="1">
		<name>GENERATE_NAME_sergeant</name>
		<icon>npc_icon_military_stalker_black2</icon> <!--<icon>ui_npc_u_stalker_military_medium_antigas_01</icon>-->
		<bio>prof_soldier_veteran_bio</bio>
		
		<class>prof_soldier_veteran</class>
		<community>military</community>
		
		<terrain_sect>stalker_military_terrain</terrain_sect>
		<critical_wound_weights>55,30,15</critical_wound_weights>
		<hit_probability_factor>1</hit_probability_factor>
		
		<rank>630</rank>
		<reputation>-20</reputation>
		
		<crouch_type>-1</crouch_type>
		<panic_threshold>0</panic_threshold>
		<money min="5000" max="20000" infinitive="0"/>
		
		<snd_config>characters_voice\human_03\military\</snd_config>
		<visual>actors\military\stalker_military_medium_antigas_01</visual>
		
		<supplies>
			<include id="soldier_t2_specnaz"/>
		</supplies>
		
	</specific_character>
	<specific_character id="prof_soldier_veteran_default2" team_default="1">
		<name>GENERATE_NAME_sergeant</name>
		<icon>npc_icon_military_stalker_green2</icon> <!--<icon>ui_npc_u_stalker_military_medium_antigas_01</icon>-->
		<bio>prof_soldier_veteran_bio</bio>
		
		<class>prof_soldier_veteran</class>
		<community>military</community>
		
		<terrain_sect>stalker_military_terrain</terrain_sect>
		<critical_wound_weights>55,30,15</critical_wound_weights>
		<hit_probability_factor>1</hit_probability_factor>
		
		<rank>650</rank>
		<reputation>-20</reputation>
		
		<crouch_type>-1</crouch_type>
		<panic_threshold>0</panic_threshold>
		<money min="5000" max="20000" infinitive="0"/>
		
		<snd_config>characters_voice\human_03\military\</snd_config>
		<visual>actors\military\stalker_military_medium_antigas_01</visual>
		
		<supplies>
			<include id="soldier_t2_specnaz"/>
		</supplies>
		
	</specific_character>
	<specific_character id="prof_soldier_veteran_default3" team_default="1">
		<name>GENERATE_NAME_sergeant</name>
		<icon>npc_icon_military_stalker_green2</icon> <!--<icon>ui_npc_u_stalker_military_medium_antigas_01</icon>-->
		<bio>prof_soldier_veteran_bio</bio>
		
		<class>prof_soldier_veteran</class>
		<community>military</community>
		
		<terrain_sect>stalker_military_terrain</terrain_sect>
		<critical_wound_weights>55,30,15</critical_wound_weights>
		<hit_probability_factor>1</hit_probability_factor>
		
		<rank>700</rank>
		<reputation>-20</reputation>
		
		<crouch_type>-1</crouch_type>
		<panic_threshold>0</panic_threshold>
		<money min="5000" max="20000" infinitive="0"/>
		
		<snd_config>characters_voice\human_03\military\</snd_config>
		<visual>actors\military\stalker_military_medium_antigas_01</visual>
		
		<supplies>
			<include id="soldier_t2_specnaz"/>
		</supplies>
		
	</specific_character>
	<specific_character id="prof_soldier_veteran_default4" team_default="1">
		<name>GENERATE_NAME_sergeant</name>
		<icon>npc_icon_military_stalker_black1</icon> <!--<icon>ui_npc_u_stalker_military_medium_antigas_01</icon>-->
		<bio>prof_soldier_veteran_bio</bio>
		
		<class>prof_soldier_veteran</class>
		<community>military</community>
		
		<terrain_sect>stalker_military_terrain</terrain_sect>
		<critical_wound_weights>55,30,15</critical_wound_weights>
		<hit_probability_factor>1</hit_probability_factor>
		
		<rank>730</rank>
		<reputation>-20</reputation>
		
		<crouch_type>-1</crouch_type>
		<panic_threshold>0</panic_threshold>
		<money min="5000" max="20000" infinitive="0"/>
		
		<snd_config>characters_voice\human_03\military\</snd_config>
		<visual>actors\military\stalker_military_ultraheavy_helmet_01</visual>
		
		<supplies>
			<include id="soldier_t2_specnaz"/>
		</supplies>
		
	</specific_character>
	<specific_character id="prof_soldier_veteran_default5" team_default="1">
		<name>GENERATE_NAME_sergeant</name>
		<icon>npc_icon_military_stalker_black1</icon> <!--<icon>ui_npc_u_stalker_military_medium_antigas_01</icon>-->
		<bio>prof_soldier_veteran_bio</bio>
		
		<class>prof_soldier_veteran</class>
		<community>military</community>
		
		<terrain_sect>stalker_military_terrain</terrain_sect>
		<critical_wound_weights>55,30,15</critical_wound_weights>
		<hit_probability_factor>1</hit_probability_factor>
		
		<rank>750</rank>
		<reputation>-20</reputation>
		
		<crouch_type>-1</crouch_type>
		<panic_threshold>0</panic_threshold>
		<money min="5000" max="20000" infinitive="0"/>
		
		<snd_config>characters_voice\human_03\military\</snd_config>
		<visual>actors\military\stalker_military_ultraheavy_helmet_01</visual>
		
		<supplies>
			<include id="soldier_t2_specnaz"/>
		</supplies>
		
	</specific_character>
	<specific_character id="prof_soldier_veteran_default6" team_default="1">
		<name>GENERATE_NAME_sergeant</name>
		<icon>npc_icon_military_stalker_green1</icon> <!--<icon>ui_npc_u_stalker_military_medium_antigas_01</icon>-->
		<bio>prof_soldier_veteran_bio</bio>
		
		<class>prof_soldier_veteran</class>
		<community>military</community>
		
		<terrain_sect>stalker_military_terrain</terrain_sect>
		<critical_wound_weights>55,30,15</critical_wound_weights>
		<hit_probability_factor>1</hit_probability_factor>
		
		<rank>800</rank>
		<reputation>-20</reputation>
		
		<crouch_type>-1</crouch_type>
		<panic_threshold>0</panic_threshold>
		<money min="5000" max="20000" infinitive="0"/>
		
		<snd_config>characters_voice\human_03\military\</snd_config>
		<visual>actors\military\stalker_military_heavy_helmet_01</visual>
		
		<supplies>
			<include id="soldier_t2_specnaz"/>
		</supplies>
		
	</specific_character>
	<specific_character id="prof_soldier_veteran_default7" team_default="1">
		<name>GENERATE_NAME_sergeant</name>
		<icon>npc_icon_military_stalker_green1</icon> <!--<icon>ui_npc_u_stalker_military_medium_antigas_01</icon>-->
		<bio>prof_soldier_veteran_bio</bio>
		
		<class>prof_soldier_veteran</class>
		<community>military</community>
		
		<terrain_sect>stalker_military_terrain</terrain_sect>
		<critical_wound_weights>55,30,15</critical_wound_weights>
		<hit_probability_factor>1</hit_probability_factor>
		
		<rank>830</rank>
		<reputation>-20</reputation>
		
		<crouch_type>-1</crouch_type>
		<panic_threshold>0</panic_threshold>
		<money min="5000" max="20000" infinitive="0"/>
		
		<snd_config>characters_voice\human_03\military\</snd_config>
		<visual>actors\military\stalker_military_heavy_helmet_01</visual>
		
		<supplies>
			<include id="soldier_t2_specnaz"/>
		</supplies>
		
	</specific_character>
	<specific_character id="prof_soldier_veteran_default8" team_default="1">
		<name>GENERATE_NAME_sergeant</name>
		<icon>npc_icon_military_stalker_green1</icon> <!--<icon>ui_npc_u_stalker_military_medium_antigas_01</icon>-->
		<bio>prof_soldier_veteran_bio</bio>
		
		<class>prof_soldier_veteran</class>
		<community>military</community>
		
		<terrain_sect>stalker_military_terrain</terrain_sect>
		<critical_wound_weights>55,30,15</critical_wound_weights>
		<hit_probability_factor>1</hit_probability_factor>
		
		<rank>880</rank>
		<reputation>-20</reputation>
		
		<crouch_type>-1</crouch_type>
		<panic_threshold>0</panic_threshold>
		<money min="5000" max="20000" infinitive="0"/>
		
		<snd_config>characters_voice\human_03\military\</snd_config>
		<visual>actors\military\stalker_military_heavy_helmet_01</visual>
		
		<supplies>
			<include id="soldier_t2_specnaz"/>
		</supplies>
		
	</specific_character>
	
	<!-- ************************** master ************************** -->
	
	<specific_character id="prof_soldier_master_default1" team_default="1">
		<name>GENERATE_NAME_captain</name>
		<icon>ui_npc_u_stalker_military_light_beret_01</icon> <!--<icon>npc_icon_soldier_beret</icon>-->
		<bio>prof_soldier_master_bio</bio>
		
		<class>prof_soldier_master</class>
		<community>military</community>
		
		<terrain_sect>stalker_military_terrain</terrain_sect>
		<critical_wound_weights>55,30,15</critical_wound_weights>
		<hit_probability_factor>1</hit_probability_factor>
		
		<rank>910</rank>
		<reputation>-20</reputation>
		
		<crouch_type>-1</crouch_type>
		<panic_threshold>0</panic_threshold>
		<money min="3000" max="5000" infinitive="0"/>
		
		<snd_config>characters_voice\human_02\military\</snd_config>
		<visual>actors\military\stalker_military_light_beret_01</visual>
		
		<supplies>
			<include id="soldier_t2_specnaz"/>
		</supplies>
		
	</specific_character>
	<specific_character id="prof_soldier_master_default2" team_default="1">
		<name>GENERATE_NAME_captain</name>
		<icon>ui_npc_u_stalker_military_light_beret_02</icon> <!--<icon>npc_icon_soldier_beret</icon>-->
		<bio>prof_soldier_master_bio</bio>
		
		<class>prof_soldier_master</class>
		<community>military</community>
		
		<terrain_sect>stalker_military_terrain</terrain_sect>
		<critical_wound_weights>55,30,15</critical_wound_weights>
		<hit_probability_factor>1</hit_probability_factor>
		
		<rank>930</rank>
		<reputation>-20</reputation>
		
		<crouch_type>-1</crouch_type>
		<panic_threshold>0</panic_threshold>
		<money min="3000" max="5000" infinitive="0"/>
		
		<snd_config>characters_voice\human_02\military\</snd_config>
		<visual>actors\military\stalker_military_light_beret_02</visual>
		
		<supplies>
			<include id="soldier_t2_specnaz"/>
		</supplies>
		
	</specific_character>
	<specific_character id="prof_soldier_master_default3" team_default="1">
		<name>GENERATE_NAME_captain</name>
		<icon>ui_npc_u_stalker_military_light_beret_01</icon> <!--<icon>npc_icon_soldier_beret</icon>-->
		<bio>prof_soldier_master_bio</bio>
		
		<class>prof_soldier_master</class>
		<community>military</community>
		
		<terrain_sect>stalker_military_terrain</terrain_sect>
		<critical_wound_weights>55,30,15</critical_wound_weights>
		<hit_probability_factor>1</hit_probability_factor>
		
		<rank>940</rank>
		<reputation>-20</reputation>
		
		<crouch_type>-1</crouch_type>
		<panic_threshold>0</panic_threshold>
		<money min="3000" max="5000" infinitive="0"/>
		
		<snd_config>characters_voice\human_02\military\</snd_config>
		<visual>actors\military\stalker_military_light_beret_03</visual>
		
		<supplies>
			<include id="soldier_t2_specnaz"/>
		</supplies>
		
	</specific_character>
	<specific_character id="prof_soldier_master_default4" team_default="1">
		<name>GENERATE_NAME_captain</name>
		<icon>ui_npc_u_stalker_military_light_beret_03</icon> <!--<icon>npc_icon_soldier_beret</icon>-->
		<bio>prof_soldier_master_bio</bio>
		
		<class>prof_soldier_master</class>
		<community>military</community>
		
		<terrain_sect>stalker_military_terrain</terrain_sect>
		<critical_wound_weights>55,30,15</critical_wound_weights>
		<hit_probability_factor>1</hit_probability_factor>
		
		<rank>950</rank>
		<reputation>-20</reputation>
		
		<crouch_type>-1</crouch_type>
		<panic_threshold>0</panic_threshold>
		<money min="3000" max="5000" infinitive="0"/>
		
		<snd_config>characters_voice\human_02\military\</snd_config>
		<visual>actors\military\stalker_military_light_beret_03</visual>
		
		<supplies>
			<include id="soldier_t2_specnaz"/>
		</supplies>
		
	</specific_character>
	<specific_character id="prof_soldier_master_default5" team_default="1">
		<name>GENERATE_NAME_captain</name>
		<icon>ui_npc_u_stalker_military_medium_helmet_01</icon> <!--<icon>npc_icon_soldier_beret</icon>-->
		<bio>prof_soldier_master_bio</bio>
		
		<class>prof_soldier_master</class>
		<community>military</community>
		
		<terrain_sect>stalker_military_terrain</terrain_sect>
		<critical_wound_weights>55,30,15</critical_wound_weights>
		<hit_probability_factor>1</hit_probability_factor>
		
		<rank>970</rank>
		<reputation>-20</reputation>
		
		<crouch_type>-1</crouch_type>
		<panic_threshold>0</panic_threshold>
		<money min="3000" max="5000" infinitive="0"/>
		
		<snd_config>characters_voice\human_02\military\</snd_config>
		<visual>actors\military\stalker_military_medium_helmet_01</visual>
		
		<supplies>
			<include id="soldier_t2_specnaz"/>
		</supplies>
		
	</specific_character>
	<specific_character id="prof_soldier_master_default6" team_default="1">
		<name>GENERATE_NAME_captain</name>
		<icon>ui_npc_u_stalker_military_light_beret_01</icon>
		<bio>prof_soldier_master_bio</bio>
		
		<class>prof_soldier_master</class>
		<community>military</community>
		
		<terrain_sect>stalker_military_terrain</terrain_sect>
		<critical_wound_weights>55,30,15</critical_wound_weights>
		<hit_probability_factor>1</hit_probability_factor>
		
		<rank>980</rank>
		<reputation>-20</reputation>
		
		<crouch_type>-1</crouch_type>
		<panic_threshold>0</panic_threshold>
		<money min="3000" max="5000" infinitive="0"/>
		
		<snd_config>characters_voice\human_02\military\</snd_config>
		<visual>actors\military\stalker_military_light_beret_01</visual>
		
		<supplies>
			<include id="soldier_t2_specnaz"/>
		</supplies>
		
	</specific_character>
	
	
<!---------------------------SVOBODA PROFILES----------------------->

<!---------------------------SVOBODA SPECNAZ----------------------->
	<specific_character id="mil_Svoboda_specnaz" team_default = "1">
		<name>GENERATE_NAME_stalker</name>
		<icon>ui_npc_u_stalker_svoboda_medium_antigas_01</icon>
		<map_icon x="5" y="0"></map_icon>
		<bio>mil_Svoboda_specnaz_bio</bio>

		<team>Svoboda_specnaz</team>

        <snd_config>characters_voice\human_03\freedom\</snd_config>
		<crouch_type>-1</crouch_type>

		<class>mil_Svoboda_specnaz</class>
		<community>freedom</community> <terrain_sect>stalker_freedom_terrain</terrain_sect>

		<rank>679</rank>
		<reputation>110</reputation>

		<visual>actors\svoboda\stalker_svoboda_medium_antigas_01</visual>
		<supplies>
			<include id="svoboda_t2_specnaz"/>
		</supplies>
		
#include "gameplay\character_criticals_5.xml"
#include "gameplay\character_dialogs.xml"
	</specific_character>

<!---------------------------SVOBODA REGULAR----------------------->
	<specific_character id="mil_Svoboda_regular" team_default = "1">
		<name>GENERATE_NAME_stalker</name>
		<icon>ui_npc_u_stalker_svoboda_light_mask_03</icon>
		<map_icon x="5" y="0"></map_icon>
		<bio>mil_Svoboda_regular_bio</bio>

		<team>Svoboda_regular</team>

        <snd_config>characters_voice\human_01\freedom\</snd_config>
		<crouch_type>-1</crouch_type>
		
		<class>mil_Svoboda_regular</class>
		<community>freedom</community> <terrain_sect>stalker_freedom_terrain</terrain_sect>
		
		<rank>368</rank>
		<reputation>74</reputation>

		<visual>actors\svoboda\stalker_svoboda_light_antigas_02</visual>
		<supplies>
			<include id="svoboda_t2_regular"/>
		</supplies>
		
#include "gameplay\character_criticals_5.xml"
#include "gameplay\character_dialogs.xml"
	</specific_character>
<!---------------------------SVOBODA SNIPER---------------------->
	<specific_character id="mil_Svoboda_sniper" team_default = "1">
		<name>GENERATE_NAME_stalker</name>
		<icon>ui_npc_u_stalker_svoboda_medium_mask_02</icon>
		<map_icon x="5" y="0"></map_icon>
		<bio>mil_Svoboda_sniper_bio</bio>

		<team>Svoboda_sniper</team>

        <snd_config>characters_voice\human_01\freedom\</snd_config>
		<crouch_type>-1</crouch_type>
		
		<class>mil_Svoboda_sniper</class>
		<community>freedom</community> <terrain_sect>stalker_freedom_terrain</terrain_sect>

		<rank>560</rank>
		<reputation>81</reputation>

		<visual>actors\svoboda\stalker_svoboda_medium_mask_02</visual>
		<supplies>
			<include id="svoboda_t2_sniper"/>
		</supplies>

#include "gameplay\character_criticals_5.xml"
#include "gameplay\character_dialogs.xml"
	</specific_character>
<!---------------------------SVOBODA SPECNAZ STUKACH---------------------->
	<specific_character id="mil_Svoboda_stukach" team_default = "1">
		<name>mil_Svoboda_stukach_name</name>
		<icon>ui_npc_u_stalker_svoboda_uniq_face_01</icon>
		<map_icon x="2" y="0"></map_icon>
		<bio>mil_Svoboda_stukach_bio</bio>

		<team>Svoboda_stukach</team>

        <snd_config>characters_voice\human_01\freedom\</snd_config>
		<crouch_type>-1</crouch_type>
		
		<class>mil_Svoboda_stukach</class>
		<community>freedom</community> <terrain_sect>stalker_freedom_terrain</terrain_sect>

		<rank>540</rank>
		<reputation>58</reputation>

		<visual>actors\svoboda\stalker_svoboda_uniq_face_01</visual>
		<supplies>
			<include id="svoboda_t2_veteran_shotgun"/>
		</supplies>
		
#include "gameplay\character_criticals_5.xml"	
#include "gameplay\character_dialogs.xml"
	</specific_character>
<!---------------------------SVOBODA MASTER----------------------->
	<specific_character id="mil_Svoboda_master" team_default = "1">
		<name>GENERATE_NAME_stalker</name>
		<icon>ui_npc_u_stalker_svoboda_light_mask_03</icon>
		<map_icon x="5" y="0"></map_icon>
		<bio>mil_Svoboda_master_bio</bio>

		<team>Svoboda_master</team>
		
		<class>mil_Svoboda_master</class>
		<community>freedom</community> <terrain_sect>stalker_freedom_terrain</terrain_sect>

        <snd_config>characters_voice\human_03\freedom\</snd_config>
		<crouch_type>0</crouch_type>
		
		<rank>930</rank>
		<reputation>126</reputation>

		<visual>actors\svoboda\stalker_svoboda_light_antigas_02</visual>
		<supplies>
			<include id="svoboda_t2_specnaz"/>
		</supplies>
		
#include "gameplay\character_criticals_5.xml"
#include "gameplay\character_dialogs.xml"			
	</specific_character>
	<!--freeplay dudes-->
	
	<specific_character id="mil_task_controller" no_random = "1">  
		<name>mil_task_controller_name</name>  
		<icon>ui_npc_monster_kontroler</icon>  
		<bio>mil_task_controller_bio</bio>  
	  
		<class>mil_task_controller</class>
		<community>trader</community>
		<visual>monsters\kontroler\kontroler</visual>
		<rank>330</rank>  
		<reputation>23</reputation>
		<supplies>

		</supplies>  
		<start_dialog>mil_task_controller_dialog</start_dialog>  
	</specific_character>
	
	<specific_character id="mil_task_mad_guy" team_default = "1">
		<name>mil_task_mad_guy_name</name>
		<icon>ui_npc_u_stalker_neutral_light_mask_04</icon>
		<map_icon x="0" y="0"></map_icon>
		<bio>sim_stalker_general_bio</bio>

		<class>mil_task_mad_guy</class>
		<community>stranger</community> <terrain_sect>stalker_terrain</terrain_sect>
		<money min="600" max="2000" infinitive="0"></money>
		
		<rank>324</rank>
		<reputation>0</reputation>
 
		<visual>actors\neutral\stalker_neutral_light_mask_03</visual>
		<snd_config>characters_voice\human_01\stalker\</snd_config>
		<crouch_type>-1</crouch_type>

		<supplies>
		</supplies>

#include "gameplay\character_criticals_4.xml"

		<start_dialog>mil_task_mad_guy_dialog</start_dialog>
	</specific_character>

	<specific_character id="mil_lager_guide" team_default = "2">
		<name>mil_lager_guide_name</name>
		<icon>ui_npc_no_data_avaliable</icon>
		
		<community>stalker</community>
		<rank>350</rank>
		<reputation>350</reputation>
		<snd_config>characters_voice\human_03\stalker\</snd_config>

		<visual>actors\military\stalker_military_heavy_antigas_01</visual>
		<supplies>
			<include id="weapon_akm_ap"/>
			<include id="stalker_veteran_common"/>
		</supplies>

		<invulnerable>true</invulnerable>
        <actor_dialog>guider_dialog</actor_dialog>
		<map_spot_pointer>guide_map_spot</map_spot_pointer>

#include "gameplay\character_criticals_5.xml"
	</specific_character>


</xml>
